nemos/__init__.py
nemos/_observation_model_builder.py
nemos/_regularizer_builder.py
nemos/base_class.py
nemos/base_regressor.py
nemos/convolve.py
nemos/exceptions.py
nemos/identifiability_constraints.py
nemos/inverse_link_function_utils.py
nemos/observation_models.py
nemos/proximal_operator.py
nemos/pytrees.py
nemos/regularizer.py
nemos/simulation.py
nemos/tree_utils.py
nemos/type_casting.py
nemos/typing.py
nemos/utils.py
nemos/validation.py
nemos/_documentation_utils/__init__.py
nemos/_documentation_utils/_myst_nb_glue.py
nemos/_documentation_utils/plotting.py
nemos/_inspect_utils/__init__.py
nemos/_inspect_utils/inspect_utils.py
nemos/basis/__init__.py
nemos/basis/_basis.py
nemos/basis/_basis_mixin.py
nemos/basis/_check_basis.py
nemos/basis/_composition_utils.py
nemos/basis/_custom_basis.py
nemos/basis/_decaying_exponential.py
nemos/basis/_fourier_basis.py
nemos/basis/_identity.py
nemos/basis/_raised_cosine_basis.py
nemos/basis/_spline_basis.py
nemos/basis/_transformer_basis.py
nemos/basis/_zero_basis.py
nemos/basis/basis.py
nemos/fetch/__init__.py
nemos/fetch/fetch_data.py
nemos/glm/__init__.py
nemos/glm/classifier_glm.py
nemos/glm/glm.py
nemos/glm/initialize_parameters.py
nemos/glm/params.py
nemos/glm/validation.py
nemos/glm_hmm/__init__.py
nemos/glm_hmm/expectation_maximization.py
nemos/io/__init__.py
nemos/io/io.py
nemos/solvers/__init__.py
nemos/solvers/_abstract_solver.py
nemos/solvers/_aux_helpers.py
nemos/solvers/_compute_defaults.py
nemos/solvers/_fista.py
nemos/solvers/_jaxopt_adapter.py
nemos/solvers/_jaxopt_solvers.py
nemos/solvers/_optax_optimistix_solvers.py
nemos/solvers/_optimistix_adapter.py
nemos/solvers/_optimistix_solvers.py
nemos/solvers/_solver_adapter.py
nemos/solvers/_solver_doc_helper.py
nemos/solvers/_solver_registry.py
nemos/solvers/_svrg.py
nemos/solvers/_svrg_defaults.py
nemos/styles/__init__.py
nemos/styles/nemos.mplstyle
nemos/third_party/README.md
nemos-0.2.6.dist-info/licenses/LICENSE
nemos-0.2.6.dist-info/METADATA
nemos-0.2.6.dist-info/WHEEL
nemos-0.2.6.dist-info/top_level.txt
nemos-0.2.6.dist-info/RECORD
