Metadata-Version: 2.4
Name: nemos
Version: 0.2.6
Summary: NEural MOdelS, a statistical modeling framework for neuroscience.
Author: nemos authors
License: MIT License
Keywords: neuroscience,Poisson-GLM
Classifier: Intended Audience :: Science/Research
Classifier: Natural Language :: English
Classifier: Programming Language :: Python :: 3
Classifier: Programming Language :: Python :: 3.10
Classifier: Programming Language :: Python :: 3.11
Classifier: Programming Language :: Python :: 3.12
Classifier: Programming Language :: Python :: 3.13
Requires-Python: <3.14,>=3.10
License-File: LICENSE
Requires-Dist: jax>=0.4.28
Requires-Dist: numpy>1.20
Requires-Dist: scipy>=1.10
Requires-Dist: typing_extensions>=4.6
Requires-Dist: pynapple>=0.10.1
Requires-Dist: scikit-learn
Requires-Dist: optimistix>=0.0.11
Requires-Dist: optax>=0.2.5
Provides-Extra: dev
Requires-Dist: black; extra == "dev"
Requires-Dist: isort; extra == "dev"
Requires-Dist: pip-tools; extra == "dev"
Requires-Dist: ruff; extra == "dev"
Requires-Dist: pytest; extra == "dev"
Requires-Dist: pytest-xdist; extra == "dev"
Requires-Dist: flake8; extra == "dev"
Requires-Dist: coverage; extra == "dev"
Requires-Dist: pytest-cov; extra == "dev"
Requires-Dist: statsmodels; extra == "dev"
Requires-Dist: scikit-learn; extra == "dev"
Requires-Dist: matplotlib>=3.7; extra == "dev"
Requires-Dist: pooch; extra == "dev"
Requires-Dist: dandi; extra == "dev"
Requires-Dist: seaborn; extra == "dev"
Requires-Dist: myst-nb; extra == "dev"
Requires-Dist: hmmlearn; extra == "dev"
Requires-Dist: tox-uv; extra == "dev"
Provides-Extra: docs
Requires-Dist: numpydoc; extra == "docs"
Requires-Dist: sphinx; extra == "docs"
Requires-Dist: pydata-sphinx-theme; extra == "docs"
Requires-Dist: sphinx-autodoc-typehints; extra == "docs"
Requires-Dist: sphinx-copybutton; extra == "docs"
Requires-Dist: sphinx-design; extra == "docs"
Requires-Dist: sphinx-issues; extra == "docs"
Requires-Dist: sphinxcontrib-apidoc; extra == "docs"
Requires-Dist: sphinxcontrib-bibtex; extra == "docs"
Requires-Dist: sphinx-togglebutton; extra == "docs"
Requires-Dist: sphinx_code_tabs; extra == "docs"
Requires-Dist: sphinxemoji; extra == "docs"
Requires-Dist: myst-parser; extra == "docs"
Requires-Dist: myst-nb; extra == "docs"
Requires-Dist: dandi; extra == "docs"
Requires-Dist: sphinx-autobuild; extra == "docs"
Requires-Dist: sphinx-contributors; extra == "docs"
Requires-Dist: scikit-learn; extra == "docs"
Requires-Dist: dandi; extra == "docs"
Requires-Dist: matplotlib>=3.7; extra == "docs"
Requires-Dist: seaborn; extra == "docs"
Requires-Dist: pooch; extra == "docs"
Requires-Dist: ipywidgets; extra == "docs"
Requires-Dist: ipykernel; extra == "docs"
Requires-Dist: patsy; extra == "docs"
Requires-Dist: tqdm; extra == "docs"
Provides-Extra: examples
Requires-Dist: scikit-learn; extra == "examples"
Requires-Dist: dandi; extra == "examples"
Requires-Dist: matplotlib>=3.7; extra == "examples"
Requires-Dist: seaborn; extra == "examples"
Requires-Dist: pooch; extra == "examples"
Requires-Dist: fsspec; extra == "examples"
Requires-Dist: patsy; extra == "examples"
Requires-Dist: tqdm; extra == "examples"
Provides-Extra: jaxopt
Requires-Dist: jaxopt>=0.6; extra == "jaxopt"
Dynamic: license-file
